mafiagg/__init__.py
mafiagg/client.py
mafiagg/credential_manager.py
mafiagg/decks.py
mafiagg/roles.py
mafiagg/room.py
mafiagg/settings.py
mafiagg/setups.py
mafiagg/user.py
mafiagg/bot/__init__.py
mafiagg/bot/botbase.py
mafiagg/bot/wsbase.py
mafiagg/chatbot/agent.py
mafiagg/chatbot/chat.py
mafiagg/chatbot/llm.py
mafiagg/chatbot/nodes.py
mafiagg/chatbot/state.py
mafiagg/chatbot/tools/__init__.py
mafiagg/chatbot/tools/wikipedia_tool.py
mafiagg/helper/custom_exceptions.py
mafiagg/helper/decorators.py
mafiagg/helper/tools.py
mafiagg/models/models.py
mafiagg-1.0.4.dist-info/METADATA
mafiagg-1.0.4.dist-info/WHEEL
mafiagg-1.0.4.dist-info/top_level.txt
mafiagg-1.0.4.dist-info/RECORD
