Metadata-Version: 2.1
Name: mafiagg
Version: 1.0.4
Summary: A Python wrapper for the MafiaGG API
Home-page: https://github.com/blacksmithop/MafiaggBot
Author: blacksmithop
License: MIT
Project-URL: Documentation, https://blacksmithop.github.io/MafiaggBot/
Project-URL: Issue tracker, https://github.com/blacksmithop/MafiaggBot/issues
Classifier: Development Status :: 5 - Production/Stable
Classifier: License :: OSI Approved :: MIT License
Classifier: Intended Audience :: Developers
Classifier: Natural Language :: English
Classifier: Operating System :: OS Independent
Classifier: Programming Language :: Python :: 3.8
Classifier: Programming Language :: Python :: 3.9
Classifier: Programming Language :: Python :: 3.10
Classifier: Programming Language :: Python :: 3.11
Classifier: Topic :: Internet
Classifier: Topic :: Software Development :: Libraries
Classifier: Topic :: Software Development :: Libraries :: Python Modules
Classifier: Topic :: Utilities
Classifier: Typing :: Typed
Requires-Python: >=3.8.0
Requires-Dist: aiohappyeyeballs==2.4.3
Requires-Dist: aiohttp==3.11.7
Requires-Dist: aiosignal==1.3.1
Requires-Dist: annotated-types==0.6.0
Requires-Dist: anyio==4.6.2.post1
Requires-Dist: attrs==24.2.0
Requires-Dist: Babel==2.14.0
Requires-Dist: beautifulsoup4==4.12.2
Requires-Dist: black==23.12.1
Requires-Dist: cachetools==5.5.0
Requires-Dist: certifi==2023.11.17
Requires-Dist: charset-normalizer==3.3.2
Requires-Dist: click==8.1.7
Requires-Dist: colorama==0.4.6
Requires-Dist: dataclasses-json==0.6.7
Requires-Dist: docutils==0.20.1
Requires-Dist: frozenlist==1.5.0
Requires-Dist: ghp-import==2.1.0
Requires-Dist: google-ai-generativelanguage==0.6.10
Requires-Dist: google-api-core==2.23.0
Requires-Dist: google-api-python-client==2.154.0
Requires-Dist: google-auth==2.36.0
Requires-Dist: google-auth-httplib2==0.2.0
Requires-Dist: google-generativeai==0.8.3
Requires-Dist: googleapis-common-protos==1.66.0
Requires-Dist: greenlet==3.1.1
Requires-Dist: grpcio==1.68.0
Requires-Dist: grpcio-status==1.68.0
Requires-Dist: h11==0.14.0
Requires-Dist: httpcore==1.0.7
Requires-Dist: httplib2==0.22.0
Requires-Dist: httpx==0.27.2
Requires-Dist: httpx-sse==0.4.0
Requires-Dist: idna==3.6
Requires-Dist: importlib-metadata==7.0.1
Requires-Dist: jaraco.classes==3.3.0
Requires-Dist: Jinja2==3.1.2
Requires-Dist: jsonpatch==1.33
Requires-Dist: jsonpointer==3.0.0
Requires-Dist: keyring==24.3.0
Requires-Dist: langchain==0.3.8
Requires-Dist: langchain-community==0.3.8
Requires-Dist: langchain-core==0.3.21
Requires-Dist: langchain-google-genai==2.0.5
Requires-Dist: langchain-ollama==0.2.0
Requires-Dist: langchain-text-splitters==0.3.2
Requires-Dist: langgraph==0.2.53
Requires-Dist: langgraph-checkpoint==2.0.6
Requires-Dist: langgraph-sdk==0.1.36
Requires-Dist: langsmith==0.1.146
Requires-Dist: Markdown==3.5.1
Requires-Dist: markdown-it-py==3.0.0
Requires-Dist: MarkupSafe==2.1.3
Requires-Dist: marshmallow==3.23.1
Requires-Dist: mdurl==0.1.2
Requires-Dist: mergedeep==1.3.4
Requires-Dist: mkdocs==1.5.3
Requires-Dist: mkdocs-material==9.5.3
Requires-Dist: mkdocs-material-extensions==1.3.1
Requires-Dist: more-itertools==10.1.0
Requires-Dist: msgpack==1.1.0
Requires-Dist: multidict==6.1.0
Requires-Dist: mypy-extensions==1.0.0
Requires-Dist: nh3==0.2.15
Requires-Dist: numpy==1.26.4
Requires-Dist: ollama==0.4.1
Requires-Dist: orjson==3.10.12
Requires-Dist: packaging==23.2
Requires-Dist: paginate==0.5.6
Requires-Dist: pathspec==0.12.1
Requires-Dist: pkginfo==1.9.6
Requires-Dist: platformdirs==4.1.0
Requires-Dist: propcache==0.2.0
Requires-Dist: proto-plus==1.25.0
Requires-Dist: protobuf==5.28.3
Requires-Dist: pyasn1==0.6.1
Requires-Dist: pyasn1_modules==0.4.1
Requires-Dist: pydantic==2.10.1
Requires-Dist: pydantic-settings==2.6.1
Requires-Dist: pydantic_core==2.27.1
Requires-Dist: Pygments==2.17.2
Requires-Dist: pymdown-extensions==10.7
Requires-Dist: pyparsing==3.2.0
Requires-Dist: python-dateutil==2.8.2
Requires-Dist: python-dotenv==1.0.0
Requires-Dist: pywin32-ctypes==0.2.2
Requires-Dist: PyYAML==6.0.1
Requires-Dist: pyyaml_env_tag==0.1
Requires-Dist: readme-renderer==42.0
Requires-Dist: regex==2023.12.25
Requires-Dist: requests==2.31.0
Requires-Dist: requests-toolbelt==1.0.0
Requires-Dist: rfc3986==2.0.0
Requires-Dist: rich==13.7.0
Requires-Dist: rsa==4.9
Requires-Dist: six==1.16.0
Requires-Dist: sniffio==1.3.1
Requires-Dist: soupsieve==2.5
Requires-Dist: SQLAlchemy==2.0.35
Requires-Dist: tenacity==9.0.0
Requires-Dist: tomli==2.0.1
Requires-Dist: tqdm==4.67.1
Requires-Dist: twine==4.0.2
Requires-Dist: typing-inspect==0.9.0
Requires-Dist: typing_extensions==4.12.2
Requires-Dist: uritemplate==4.1.1
Requires-Dist: urllib3==2.1.0
Requires-Dist: watchdog==3.0.0
Requires-Dist: websockets==12.0
Requires-Dist: wikipedia==1.4.0
Requires-Dist: yarl==1.18.0
Requires-Dist: zipp==3.17.0
Provides-Extra: docs
Requires-Dist: mkdocs-material==9.5.3; extra == "docs"
